[
  {
    "id": 1,
    "firstName": "John",
    "lastName": "Wick",
    "position": "Android Developer",
    "dateOfBirth": "1990-01-01"
  },
  {
    "id": 2,
    "firstName": "Christina",
    "lastName": "Doe",
    "position": "CTO",
    "dateOfBirth": "1986-07-25"
  },
  {
    "id": 3,
    "firstName": "Ivan",
    "lastName": "Ivanov",
    "position": "Data Analyst",
    "dateOfBirth": "1997-05-20"
  },
  {
    "id": 4,
    "firstName": "John",
    "lastName": "Doe",
    "position": "Data Analyst",
    "dateOfBirth": "1993-05-13"
  },
  {
    "id": 5,
    "firstName": "Samantha",
    "lastName": "Snow",
    "position": "Marketing manager",
    "dateOfBirth": "1979-02-10"
  },
  {
    "id": 6,
    "firstName": "Gregory",
    "lastName": "Grogoriev",
    "position": "SEO specialist",
    "dateOfBirth": "2003-01-10"
  },
  {
    "id": 7,
    "firstName": "Tina",
    "lastName": "Turner",
    "position": "SEO specialist",
    "dateOfBirth": "2000-01-10"
  },
  {
    "id": 8,
    "firstName": "Margareth",
    "lastName": "Turner",
    "position": "QA engineer",
    "dateOfBirth": "1992-03-10"
  },
  {
    "id": 9,
    "firstName": "Some",
    "lastName": "User",
    "position": "QA engineer",
    "dateOfBirth": "1990-03-10"
  },
  {
    "id": 10,
    "firstName": "Agent",
    "lastName": "Smith",
    "position": "Backend Developer",
    "dateOfBirth": "1986-12-10"
  },
  {
    "id": 11,
    "firstName": "Neo",
    "lastName": "Anderson",
    "position": "Backend Developer",
    "dateOfBirth": "1989-06-07"
  },
  {
    "id": 12,
    "firstName": "Max",
    "lastName": "Mad",
    "position": "Backend Developer",
    "dateOfBirth": "1990-06-07"
  },
  {
    "id": 13,
    "firstName": "John",
    "lastName": "Cena",
    "position": "Frontend Developer",
    "dateOfBirth": "1986-06-07"
  },
  {
    "id": 14,
    "firstName": "The",
    "lastName": "Rock",
    "position": "Frontend Developer",
    "dateOfBirth": "1986-06-07"
  }
]
